LICENSE.txt
README.md
setup.cfg
setup.py
cloud_functions_test/__init__.py
cloud_functions_test/cli.py
cloud_functions_test/environment.py
cloud_functions_test/exceptions.py
cloud_functions_test/functions.py
cloud_functions_test/main.py
cloud_functions_test/matching.py
cloud_functions_test/utils.py
cloud_functions_test.egg-info/PKG-INFO
cloud_functions_test.egg-info/SOURCES.txt
cloud_functions_test.egg-info/dependency_links.txt
cloud_functions_test.egg-info/entry_points.txt
cloud_functions_test.egg-info/requires.txt
cloud_functions_test.egg-info/top_level.txt
cloud_functions_test/test_classes/base_test.py
cloud_functions_test/test_classes/event_test.py
cloud_functions_test/test_classes/http_test.py