Metadata-Version: 2.1
Name: cloud-functions-test
Version: 0.0.2
Summary: Test locally GCP Cloud Functions
Home-page: https://github.com/RobinPicard/cloud-functions-test
Author: Robin Picard
Author-email: robin.picard@sciencespo.fr
License: apache-2.0
Download-URL: https://github.com/RobinPicard/cloud-functions-test/releases/download/v0.0.1/cloud-functions-test-0.0.2.tar.gz
Keywords: python,testing,tests,gcp,cloud functions
Platform: UNKNOWN
Classifier: Intended Audience :: Developers
Classifier: Programming Language :: Python
Classifier: Topic :: Software Development :: Testing
License-File: LICENSE.txt
